invenio_requests/__init__.py
invenio_requests/config.py
invenio_requests/errors.py
invenio_requests/ext.py
invenio_requests/proxies.py
invenio_requests/registry.py
invenio_requests/tasks.py
invenio_requests/webpack.py
invenio_requests/alembic/1759321170_add_index_to_request_events_request_id_.py
invenio_requests/alembic/5cd30a3503c9_create_requests_branch.py
invenio_requests/alembic/74b23178bfbe_change_datetime_types.py
invenio_requests/alembic/a14fa442680f_create_tables.py
invenio_requests/assets/semantic-ui/js/invenio_requests/InvenioRequestsApp.js
invenio_requests/assets/semantic-ui/js/invenio_requests/index.js
invenio_requests/assets/semantic-ui/js/invenio_requests/requestsAppInit.js
invenio_requests/assets/semantic-ui/js/invenio_requests/store.js
invenio_requests/assets/semantic-ui/js/invenio_requests/api/InvenioRequestApi.js
invenio_requests/assets/semantic-ui/js/invenio_requests/api/InvenioRequestEventsApi.js
invenio_requests/assets/semantic-ui/js/invenio_requests/api/api.js
invenio_requests/assets/semantic-ui/js/invenio_requests/api/index.js
invenio_requests/assets/semantic-ui/js/invenio_requests/api/serializers.js
invenio_requests/assets/semantic-ui/js/invenio_requests/components/Buttons.js
invenio_requests/assets/semantic-ui/js/invenio_requests/components/CreatorList.js
invenio_requests/assets/semantic-ui/js/invenio_requests/components/Error.js
invenio_requests/assets/semantic-ui/js/invenio_requests/components/ErrorBoundary.js
invenio_requests/assets/semantic-ui/js/invenio_requests/components/FakeInput.js
invenio_requests/assets/semantic-ui/js/invenio_requests/components/Loader.js
invenio_requests/assets/semantic-ui/js/invenio_requests/components/ModalTriggers.js
invenio_requests/assets/semantic-ui/js/invenio_requests/components/RequestTypeIcon.js
invenio_requests/assets/semantic-ui/js/invenio_requests/components/RequestsFeed.js
invenio_requests/assets/semantic-ui/js/invenio_requests/components/SharedOrMineFilter.js
invenio_requests-12.0.0.dist-info/licenses/AUTHORS.rst
invenio_requests-12.0.0.dist-info/licenses/LICENSE
invenio_requests-12.0.0.dist-info/METADATA
invenio_requests-12.0.0.dist-info/WHEEL
invenio_requests-12.0.0.dist-info/entry_points.txt
invenio_requests-12.0.0.dist-info/top_level.txt
invenio_requests-12.0.0.dist-info/RECORD
