Metadata-Version: 2.4
Name: invenio-requests
Version: 12.0.0
Summary: Invenio module for generic and customizable requests.
Home-page: https://github.com/inveniosoftware/invenio-requests
Author: CERN
Author-email: info@inveniosoftware.org
License: MIT
Keywords: invenio requests
Platform: any
Classifier: Development Status :: 5 - Production/Stable
Requires-Python: >=3.7
License-File: LICENSE
License-File: AUTHORS.rst
Requires-Dist: invenio-records-resources<10.0.0,>=9.0.0
Requires-Dist: invenio-theme<5.0.0,>=4.0.0
Requires-Dist: invenio-users-resources<11.0.0,>=10.0.0
Provides-Extra: tests
Requires-Dist: pytest-black>=0.6.0; extra == "tests"
Requires-Dist: invenio-app<4.0.0,>=3.0.0; extra == "tests"
Requires-Dist: invenio-db[mysql,postgresql]<3.0.0,>=2.2.0; extra == "tests"
Requires-Dist: pytest-invenio<5.0.0,>=4.0.0; extra == "tests"
Requires-Dist: sphinx>=4.5.0; extra == "tests"
Requires-Dist: time-machine<3.0.0,>=2.19.0; extra == "tests"
Provides-Extra: elasticsearch7
Requires-Dist: invenio-search[elasticsearch7]<4.0.0,>=3.0.0; extra == "elasticsearch7"
Provides-Extra: opensearch1
Requires-Dist: invenio-search[opensearch1]<4.0.0,>=3.0.0; extra == "opensearch1"
Provides-Extra: opensearch2
Requires-Dist: invenio-search[opensearch2]<4.0.0,>=3.0.0; extra == "opensearch2"
Dynamic: license-file
